iana_tz_coord/__init__.py
iana_tz_coord/coordinates.py
iana_tz_coord/coordinates_by_tz_name.py
iana_tz_coord/get_coordinates.py
iana_tz_coord-1.0.3.dist-info/LICENSE
iana_tz_coord-1.0.3.dist-info/METADATA
iana_tz_coord-1.0.3.dist-info/WHEEL
iana_tz_coord-1.0.3.dist-info/top_level.txt
iana_tz_coord-1.0.3.dist-info/RECORD
