Metadata-Version: 2.1
Name: iana-tz-coord
Version: 1.0.3
Summary: Get the longitude and latitude of an iana timezone's principal location
Home-page: https://github.com/zhammer/iana-tz-coord
Author: Zach Hammer
Author-email: zach.the.hammer@gmail.com
License: MIT License
Platform: UNKNOWN
